{
  "unversionedId": "Java学习/Java基础",
  "id": "Java学习/Java基础",
  "title": "概览",
  "description": "1. java是世界上最流行的编程语言，拥有超过10亿的设备运行java",
  "source": "@site/docs/Java学习/Java基础.md",
  "sourceDirName": "Java学习",
  "slug": "/Java学习/Java基础",
  "permalink": "/docs/Java学习/Java基础",
  "draft": false,
  "editUrl": "https://github.com/facebook/docusaurus/tree/main/packages/create-docusaurus/templates/shared/docs/Java学习/Java基础.md",
  "tags": [],
  "version": "current",
  "frontMatter": {
    "position": 1
  },
  "sidebar": "Records",
  "previous": {
    "title": "Java学习",
    "permalink": "/docs/category/java学习"
  },
  "next": {
    "title": "Tutorial - Extras",
    "permalink": "/docs/category/tutorial---extras"
  }
}